[{"senderKeyId":2105768844,"senderChainKey":{"iteration":1743,"seed":"YY5FqbP06pvpCNcDbCKOutRCqpED8aWCj6ZWHiZnMos="},"senderSigningKey":{"public":"BcuuzfUsvOfMBbjGfEyVsvPioe9Ornf3RvWtgMKp2nVj"},"senderMessageKeys":[{},{},{},{},{},{},{},{},{},{},{},{},{},{},{},{},{},{},{},{},{},{},{},{},{},{},{},{},{},{},{},{},{},{},{},{},{},{},{},{},{},{},{},{},{},{},{},{},{},{},{},{},{},{},{},{},{},{},{},{},{},{},{},{},{},{},{},{},{},{},{},{},{},{},{},{},{},{},{},{},{},{},{},{},{},{},{},{},{},{},{},{},{},{},{},{},{},{},{},{},{},{},{},{},{},{},{},{},{},{},{},{},{},{},{},{},{},{},{},{},{},{},{},{},{},{},{},{},{},{},{},{},{},{},{},{},{},{},{},{},{},{},{},{},{},{},{},{},{},{},{},{},{},{},{},{},{},{},{},{},{},{},{},{},{},{},{},{},{},{},{},{},{},{},{},{},{},{},{},{},{},{},{},{}]},{"senderKeyId":643181522,"senderChainKey":{"iteration":56,"seed":"pyfYP+1cU2388H+QARbE3scGaKMzfUL5uYKpLqqGTjI="},"senderSigningKey":{"public":"Bb1Z40qWNNGN0pS20FLUfVYl1FlDktqKD2fuwgWH6CEc"},"senderMessageKeys":[]}]